LICENSE
MANIFEST.in
README.rst
setup.py
django_game_info.egg-info/PKG-INFO
django_game_info.egg-info/SOURCES.txt
django_game_info.egg-info/dependency_links.txt
django_game_info.egg-info/top_level.txt
game_info/__init__.py
game_info/admin.py
game_info/models.py
game_info/processors.py
game_info/serializers.py
game_info/urls.py
game_info/views.py
game_info/management/__init__.py
game_info/management/commands/__init__.py
game_info/management/commands/update_game_info.py
game_info/migrations/0001_initial.py
game_info/migrations/__init__.py
game_info/tests/__init__.py
game_info/tests/test_admin.py
game_info/tests/test_commands.py
game_info/tests/test_models.py
game_info/tests/test_views.py