Metadata-Version: 1.1
Name: django-game-info
Version: 0.1.3
Summary: A django app to gather information from game servers.
Home-page: https://github.com/Azelphur-Servers/django-game-info
Author: Alfie "Azelphur" Day
Author-email: support@azelphur.com
License: BSD License
Platform: UNKNOWN
Classifier: Environment :: Web Environment
Classifier: Framework :: Django
Classifier: Intended Audience :: Developers
Classifier: License :: OSI Approved :: BSD License
Classifier: Operating System :: OS Independent
Classifier: Programming Language :: Python
Classifier: Programming Language :: Python
Classifier: Programming Language :: Python :: 2.6
Classifier: Programming Language :: Python :: 2.7
Classifier: Topic :: Internet :: WWW/HTTP
Classifier: Topic :: Internet :: WWW/HTTP :: Dynamic Content
